{
  "chunk_id": "the_companies_act_bangladesh___ch0__s14",
  "act_name": "The Companies Act (Bangladesh)",
  "act_number": "Act No. 18 of 1994",
  "chapter_number": "0",
  "chapter_title": "PRELIMINARY",
  "section_number": "14",
  "section_title": "Exercises of discretion by Court.",
  "content": "14. Exercises of discretion by Court.\nThe Court shall, in exercising its discretion under sections 12 and 13, have regard to the class of them, as well as to the\nrights and interests of the creditors, and may if it thinks fit, adjourn the proceedings in order that an arrangement may be\nmade to the satisfaction of the Court for the purchase of the interests of dissenting members; and may give such directions\nand make such orders as it may think expedient for facilitating or carrying into effect any such arrangement;\nProvided that no part of the share capital of the company may be expended in any such purchase.",
  "sub_sections": [],
  "illustrations": [],
  "exceptions": [],
  "explanations": [],
  "language": "en",
  "has_illustrations": false,
  "priority": 1,
  "keywords": [
    "exercises",
    "discretion",
    "court"
  ],
  "source_file": "5e1654acafde5companiesact_0.pdf",
  "page_range": [
    6,
    6
  ],
  "char_count": 616,
  "word_count": 109
}