{
  "chunk_id": "the_companies_act_bangladesh___ch0__s375",
  "act_name": "The Companies Act (Bangladesh)",
  "act_number": "Act No. 18 of 1994",
  "chapter_number": "0",
  "chapter_title": "PRELIMINARY",
  "section_number": "375",
  "section_title": "Restrictions on commencing etc. of suit after winding up order.--Where an order has been made for winding up",
  "content": "375. Restrictions on commencing etc. of suit after winding up order.--Where an order has been made for winding up\nof a company under this Part, no suit or other legal proceedings shall bee proceeded with or commenced against except by\nleave of the Court , and subject OT such terms as the Court may impose.",
  "sub_sections": [],
  "illustrations": [],
  "exceptions": [],
  "explanations": [],
  "language": "en",
  "has_illustrations": false,
  "priority": 1,
  "keywords": [
    "restrictions",
    "commencing",
    "suit",
    "after",
    "winding",
    "order",
    "where",
    "been",
    "made"
  ],
  "source_file": "5e1654acafde5companiesact_0.pdf",
  "page_range": [
    85,
    85
  ],
  "char_count": 306,
  "word_count": 55
}