{
  "chunk_id": "the_companies_act_bangladesh___ch0__s352",
  "act_name": "The Companies Act (Bangladesh)",
  "act_number": "Act No. 18 of 1994",
  "chapter_number": "0",
  "chapter_title": "PRELIMINARY",
  "section_number": "352",
  "section_title": "Application Act of companies registered but not formed under former Combines Act:-- This Act shall apply to",
  "content": "352. Application Act of companies registered but not formed under former Combines Act:-- This Act shall apply to\nevery company registered but not formed under any law in force at any time before the commencement of this Act in the\nsame manner as it is herein after in this Act. declared to apply to Combines registered but not formed under this Act:\nProvided that reference, express or impaled, to the date off registration shall be cons rend a a reference to the date at which\nthe company was registered under the said laws or any of them.",
  "sub_sections": [],
  "illustrations": [],
  "exceptions": [],
  "explanations": [],
  "language": "en",
  "has_illustrations": false,
  "priority": 1,
  "keywords": [
    "application",
    "companies",
    "registered",
    "formed",
    "under",
    "former",
    "combines",
    "shall",
    "apply"
  ],
  "source_file": "5e1654acafde5companiesact_0.pdf",
  "page_range": [
    81,
    81
  ],
  "char_count": 540,
  "word_count": 97
}