{
  "chunk_id": "the_contract_act__chii__s24",
  "act_name": "The Contract Act",
  "act_number": "ACT NO. IX OF 1872",
  "chapter_number": "II",
  "chapter_title": "OF CONTRACTS, VOIDABLE CONTRACTS AND VOID AGREEMENTS",
  "section_number": "24",
  "section_title": "If any part of a single consideration for one or more objects, or any one",
  "content": "24. If any part of a single consideration for one or more objects, or any one\nvoid, if\nor any part of any one of several considerations for a single object is\nconsiderations\nand objects unlawful, the agreement is void.\nunlawful in\nIllustration\npart\nA promises to superintend, on behalf of B, a legal manufacture of indigo, and\nan illegal traffic in other articles. B promises to pay to A a salary of 10,000\nTaka a year. The agreement is void, the object of A's promise and the\nconsiderations B's promise being in part unlawful.\nAgreement",
  "sub_sections": [],
  "illustrations": [
    "part\nA promises to superintend, on behalf of B, a legal manufacture of indigo, and\nan illegal traffic in other articles. B promises to pay to A a salary of 10,000\nTaka a year. The agreement is void, the object of A's promise and the\nconsiderations B's promise being in part unlawful.\nAgreement"
  ],
  "exceptions": [],
  "explanations": [],
  "language": "en",
  "has_illustrations": true,
  "priority": 3,
  "keywords": [
    "void",
    "agreement",
    "consideration",
    "part",
    "single",
    "more",
    "objects"
  ],
  "source_file": "act-print-26.pdf",
  "page_range": [
    11,
    11
  ],
  "char_count": 537,
  "word_count": 96
}