{
  "chunk_id": "___ch0__s211",
  "act_name": "কাম্পানী আইন",
  "act_number": "১৯৯৪ সেনর ১৮ নং আইন",
  "chapter_number": "0",
  "chapter_title": "PRELIMINARY",
  "section_number": "211",
  "section_title": "(১) অবসর গ্রহণকারী কান িনরীক্ষক বতীত অন কান বক্তেক িনরীক্ষক",
  "content": "২১১৷ (১) অবসর গ্রহণকারী কান িনরীক্ষক বতীত অন কান বক্তেক িনরীক্ষক\nিনেয়াগ ও\nঅপসারেণর িহসােব িনেয়াগ দােনর ক্ষেত্র িকংবা অবসর গ্রহণকারী কান িনরীক্ষকেক পুনরায়\nিসদ্ধান্ত\nিনেয়াগ করা যাইেব না মেম স্পষ্টভােব বািষক সাধারণ সভায় িসদ্ধান্ত গ্রহেণর ক্ষেত্র\nসম্পিকত\nিবেশষ নাটিশ প্রদােনর প্রেয়াজন হইেব।\nিবধানাবলী\n(২) কাম্পানী উক্ত নাটিশ প্রািপ্তর পর অিবলেম্ব উহার একটি অনুলিপ অবসর\nগ্রহণকারী িনরীক্ষেকর িনকট প্ররণ কিরেব।\n(৩) য ক্ষেত্র উক্ত নাটিশ দওয়া হয় এবং অবসর গ্রহণকারী িনরীক্ষক তৎসম্পেক\nলিখতভােব িনেবদন পশ কিরয়া প্রস্তািবত িসদ্ধান্ত সম্পেক সদসগণেক নাটিশ\nপ্রদােনর জন কাম্পানীেক অনুেরাধ জানান, স ক্ষেত্র, উক্ত অনুেরাধ কাম্পানীর\nিনকট িবলেম্ব পৗছােনা সেও নাটিশ দওয়া অসম্ভব না হইেল, কাম্পানী -\n(ক) উহার সদসগেণর িনকট প্রিরতব িসদ্ধােন্তর নাটিেশ উক্ত িনেবদেনর িবষয়\nউেল্লখ কিরেব; এবং\n(খ) উক্ত িনেবদন পাওয়ার পূেব বা পের যখনই উহার কান সদসগেণর িনকট\nসভার নাটিশ প্ররণ কের তখনই উক্ত সদেসর িনকট িনেবদেনর অনুলিপ প্ররণ\nকিরেব; এবং িবলেম্ব িনেবদনটি পাওয়ার কারেণ অথবা কাম্পানীর কান ত্রুটির\nকারেণ যিদ উক্ত অনুলিপ প্রিরত না হইয়া থােক, তাহা হইেল িনরীক্ষক দাবী কিরেত\nপািরেবন য, উক্ত িনেবদন উক্ত সভায় পাঠ কিরয়া শুনাইেত হইেব; এবং িতিন উক্ত\nসভায় তাহার বক্তব মৗিখকভােবও পশ করার অিধকারী হইেবন:\n\nতেব শত থােক য, যিদ কাম্পানী অথবা সংক্ষুব্ধ কান বক্ত বা অন কান বক্তর\nআেবদনক্রেম আদালত সন্তুষ্ট হয় য, মানহািনকর কান িবষেয়র অনাবশক\nপ্রচারণার জন এই ধারাবেল অিপত অিধকােরর অপববহার করা হইেতেছ, তাহা\nহইেল, আদালত উক্ত িনেবদেনর অনুলিপ প্ররণ করা হইেত এবং উহা সভায় পাঠ\nকিরয়া শুনােনা হইেত কাম্পানীেক অবাহিত িদেত পািরেব এবং আেদশ প্রদান\nকিরেত পািরেব য, উক্ত কাম্পানীর বা উক্ত বক্তর আেবদেনর উপর কাম্পানীর\nযাবতীয় খরচ, সম্পূণ বা আংিশকভােব, িনরীক্ষক পিরেশাধ কিরেবন, এমনিক িতিন\nউক্ত আেবদনপেত্র কান পক্ষ না থািকেলও।\n(৪) ধারা ২১০ এর উপ-ধারা (৬) বা (৯) এর অধীেন কান অপসারেণর িসদ্ধােন্তর\nক্ষেত্র, এই ধারার (২) ও (৩) উপ-ধারা প্রেযাজ হইেব যমন তাহা কান অবসর\nগ্রহণকারী িনরীক্ষকেক পুনিনেয়াগ না করার িসদ্ধােন্তর ক্ষেত্র প্রেযাজ হয়।\nিনরীক্ষকগেণর",
  "sub_sections": [],
  "illustrations": [],
  "exceptions": [],
  "explanations": [],
  "language": "bn",
  "has_illustrations": false,
  "priority": 1,
  "keywords": [],
  "source_file": "act-print-788.pdf",
  "page_range": [
    135,
    136
  ],
  "char_count": 1890,
  "word_count": 300
}