{
  "chunk_id": "___ch0__s199",
  "act_name": "কাম্পানী আইন",
  "act_number": "১৯৯৪ সেনর ১৮ নং আইন",
  "chapter_number": "0",
  "chapter_title": "PRELIMINARY",
  "section_number": "199",
  "section_title": "(১) যিদ ধারা ১৯৫ বা ১৯৭ ধারার অধীেন কান কাম্পানীর িবষয়ািদ",
  "content": "১৯৯৷ (১) যিদ ধারা ১৯৫ বা ১৯৭ ধারার অধীেন কান কাম্পানীর িবষয়ািদ\nকাম্পানী বা\nমােনজং তদন্ত করার জন িনযুক্ত পিরদশক তাহার তদন্ত্ম পিরচালনার উেদ্দেশ প্রেয়াজনীয়\nএেজন্ট\nবলয়া মেন কেরন য, িনম্নলিখত সংস্থা বা বক্তর িবষয়ািদরও তদন্ত কিরেত হইেব,\nইতািদর\nযথা :-\nকাজকম\nতদেন্তর ক্ষমতা\n(ক) এইরূপ অন কান িনগিমত সংস্থা যাহা সংিষ্ট সমেয় উক্ত কাম্পানীর অধীনস্থ\nবা িনয়ন্ত্রণকারী কাম্পানী িছল বা রিহয়ােছ অথবা উহার িনয়ন্ত্রণকারী কাম্পানীর\nঅধীনস্থ িছল বা রিহয়ােছ অথবা উহার অধীনস্থ কাম্পানীর িনয়ন্ত্রণকারী কাম্পানী\nিছল বা রিহয়ােছ; অথবা\n(খ) অন কান িনগিমত সংস্থা যাহার ববস্থাপনা সংিষ্ট সমেয় িনম্নলিখত কান\nবক্ত কতৃক সম্পন্ন হইেতেছ বা হইয়ােছ, যথা :-\n(অ) উক্ত িনগিমত সংস্থার এমন মােনজং এেজন্ট বা ববস্থাপনা-পিরচালক বা\nমােনজার িযিন সংিষ্ট সমেয় উক্ত কাম্পানীর মােনজং এেজন্ট বা ববস্থাপনা-\nপিরচালক বা মােনজার থােকন বা িছেলন; অথবা\n(আ) এমন বক্ত িযিন সংিষ্ট সমেয় মােনজং এেজেন্টর একজন সহেযাগী থােকন\nবা িছেলন; অথবা\n(ই) এমন বক্ত যাহার সহেযাগী িছেলন বা থােকন উক্ত মােনজং এেজন্ট; অথবা\n(গ) অন য কান িনগিমত সংস্থা যাহা সংিষ্ট সমেয় উক্ত কাম্পানী কতৃক\nপিরচালত হয় বা হইয়ােছ অথবা যাহার পিরচালক পিরষদ উক্ত কাম্পানীর\nমেনানীত বক্তবেগর সমন্বেয় গঠিত হইয়ােছ অথবা যাহা িনম্নলিখেতর িনেদশ\nঅনুসাের কাজ কিরেত অভস্ত, যথা :-\n(অ) উক্ত কাম্পানী; অথবা\n(আ) উক্ত কাম্পানীর য কান পিরচালক, অথবা\n(ই) অন এমন কাম্পানী যাহার পিরচালক পেদ অিধষ্ঠত আেছন প্রথেমাক্ত\nকাম্পানীর িনয়ন্ত্রণাধীেন বা ববস্থাপনাধীেন িনেয়াজত কমচারী বা মেনানীত বক্ত;\nঅথবা\n\n(ঘ) এমন বক্ত িযিন সংিষ্ট সমেয় উক্ত কাম্পানীর মােনজং এেজন্ট, ববস্থাপনা-\nপিরচালক অথবা মােনজার অথবা অনুরূপ মােনজং এেজেন্টর সহেযাগী থােকন\nবা িছেলন,\nতাহা হইেল, উপ-ধারা (২) এর িবধান সােপেক্ষ, পিরদশক উক্ত পিরদশন কিরেত\nপািরেবন এবং িতিন উক্ত িনগিমত সংস্থা, মােনজং এেজন্ট, ববস্থাপনা-পিরচালক,\nমােনজার অথবা মােনজং এেজেন্টর সহেযাগীর িবষয়ািদ তদন্ত কিরয়া তত্সম্পেক\nতাহার প্রিতেবদেন ততটকু উেল্লখ কিরেবন যতটকু প্রথেমাক্ত কাম্পানীর িবষয়ািদ\nতদেন্তর সিহত সম্পৃক্ত৷\n(২) উপ-ধারা (১) এর (খ) দফার (আ) বা (ই) উপ-দফায় অথবা (গ) বা (ঘ) দফায়\nবিণত ত্মগেত্র, পিরদশক সরকােরর পূব অনুেমাদন না লইয়া তাহার ক্ষমতা প্রেয়াগ\nকিরেবন না :\nতেব শত থােক য, এই উপ-ধারার অধীেন অনুেমাদন প্রদােনর পূেব সরকার এইরূপ\nঅনুেমাদন সম্পেক উক্ত িবধানসমূেহ উল্লিখত িনগিমত সংস্থা বা বক্তর আপত্ত বা\nবক্তব পশ করার জন উহােক বা তাহােক যুক্তসংগত সুেযাগ িদেব।\nদলল, সাক্ষ",
  "sub_sections": [],
  "illustrations": [],
  "exceptions": [],
  "explanations": [],
  "language": "bn",
  "has_illustrations": false,
  "priority": 1,
  "keywords": [],
  "source_file": "act-print-788.pdf",
  "page_range": [
    125,
    126
  ],
  "char_count": 2201,
  "word_count": 347
}